tutorial-2/Seven_Segment.v
module Seven_Segment (
	input wire CLK_IN,
	input wire [3:0]NUMBER_IN,
	output reg [6:0] OUTPUT
    );

	parameter zero   = 7'b1111110;  //Value for zero
	parameter one    = 7'b0110000;  //Value for one
	parameter two    = 7'b1101101;  //Value for two
	parameter three  = 7'b1111001;  //Value for three
	parameter four   = 7'b0110011;  //Value for four
	parameter five   = 7'b1011011;  //Value for five
	parameter six    = 7'b1011111;  //Value for six
	parameter seven  = 7'b1110000;  //Value for seven
	parameter eight  = 7'b1111111;  //Value for eight
	parameter nine   = 7'b1110011;  //Value for nine
	parameter A      = 7'b1110111;  //Value for A
	parameter B      = 7'b0011111;  //Value for B 
	parameter C      = 7'b1001110;  //Value for C
	parameter D      = 7'b0111101;  //Value for D
	parameter E      = 7'b1001111;  //Value for E
	parameter F      = 7'b1000111;  //Value for F

	always @(posedge CLK_IN) begin
		case(NUMBER_IN)
			4'b0000: OUTPUT <= ~zero;
			4'b0001: OUTPUT <= ~one;
			4'b0010: OUTPUT <= ~two;
			4'b0011: OUTPUT <= ~three;
			4'b0100: OUTPUT <= ~four;
			4'b0101: OUTPUT <= ~five;
			4'b0110: OUTPUT <= ~six;
			4'b0111: OUTPUT <= ~seven;
			4'b1000: OUTPUT <= ~eight;
			4'b1001: OUTPUT <= ~nine;
			4'b1010: OUTPUT <= ~A;
			4'b1011: OUTPUT <= ~B;
			4'b1100: OUTPUT <= ~C;
			4'b1101: OUTPUT <= ~D;
			4'b1110: OUTPUT <= ~E;
			4'b1111: OUTPUT <= ~F;
			default: OUTPUT <= ~zero;
		endcase
 	end
endmodule

tutorial-2/Seven_Segment_Display.v
`include "Seven_Segment.v"

module Seven_Segment_Display (
    input wire clk,
    input wire RST_N,
    input wire [15:0] Displayed_number,
    output reg [3:0] Cathode,
    output wire [6:0] Segment_out
    );

    // For modification during simulation later
    parameter startRefreshCounter = 14;
    parameter endRefreshCounter = 15;

    wire [1:0] LED_activating_counter;
    reg [3:0] Digit_number;
    reg [15:0] refresh_counter = 16'b0;

    // Creating Seven_Segment instance
    Seven_Segment i2
    (
        .CLK_IN(clk),
        .NUMBER_IN(Digit_number),
        .OUTPUT(Segment_out[6:0])
    );

    // Switch between 4 digits of display
    always @(posedge clk or negedge RST_N)
        begin
            if (RST_N==0)
                refresh_counter <= 0;
            else
                refresh_counter <= refresh_counter + 1;
        end

    // every 24M / (2^14) hz switch to next digit in 7-seg display
    assign LED_activating_counter = refresh_counter[endRefreshCounter:startRefreshCounter];

    // select digit to light up
    always @(posedge clk) begin
            case(LED_activating_counter)
            2'b00: begin
                // pull to ground for first digit
                Cathode = 4'b1000;
                Digit_number <= Displayed_number[15:11];
            end
            2'b01: begin
                // pull to ground for second digit
                Cathode = 4'b0100;
                Digit_number <= Displayed_number[10:8];
            end	
            2'b10: begin
                // pull to ground for third digit
                Cathode = 4'b0010;
                Digit_number <= Displayed_number[7:4];
            end
            2'b11: begin
                // pull to ground for fourth digit
                Cathode = 4'b0001;
                Digit_number <= Displayed_number[3:0];
            end
            default: begin
                // pull to ground for default first digit
                Cathode <= 4'b1111;
                Digit_number <= 4'b1111;
            end
            endcase
        end
    
endmodule

tutorial-2/Fibonacci_Series.v
module Fibonacci_Series ( 
    input wire CLK_IN,
    input wire RST_N,
    output wire [15:0] SEQUENCE
    );

    reg [15:0] SEQUENCE_I1,SEQUENCE_I2;

    assign SEQUENCE = RST_N ? (SEQUENCE_I1 + SEQUENCE_I2) : 16'b1;

    always @(posedge CLK_IN) begin 
        if(SEQUENCE < 16'hDAAA) begin 
            SEQUENCE_I2 = SEQUENCE_I1;
            SEQUENCE_I1 = SEQUENCE;
        end 
        else begin 
            SEQUENCE_I2 = 16'b1;
            SEQUENCE_I1 = 16'b0;
        end 
    end 
endmodule

tutorial-2/Seven_Segment_Display_Top.v
`include "Seven_Segment_Display.v"
`include "Fibonacci_Series.v"

module Seven_Segment_Display_Top (
    input wire clk,
    input wire RST_N,
    output wire [3:0] Cathode,
    output wire [6:0] Segment_out
    );

    // Signal to send number to Seven_Segment_Display module
    wire [15:0] Displayed_number;

    // For modification during simulation later
    parameter startRefreshCounter = 14;
    parameter endRefreshCounter = 15;

    // Frequency of master clock
    parameter time1 = 25'd24_000_000;  // 24 MHz counter

    // Slow clock divider
    reg [24:0] count = 24'b0;
    reg clk_slow = 1'b0;

    // Slow clock to increment number displayed
    always @(posedge clk) begin
        // Code for reset
        if(RST_N==0) begin			
            count <= 25'd0;
            clk_slow <= 1'b0;
        end
        if(count == time1) begin
            count <= 25'd0;
            clk_slow <= ~clk_slow;      
            end
        else begin 
            count <= count + 1'b1;
            end
        end

    // Creating Fibonacci_Series instance
    Fibonacci_Series i1
    (
        .CLK_IN(clk_slow),
        .RST_N(RST_N),
        .SEQUENCE(Displayed_number)
    );

    // Creating 4-digit seven segment display instance
    Seven_Segment_Display #(
        .startRefreshCounter(startRefreshCounter),
        .endRefreshCounter(endRefreshCounter)
    ) Seven_Segment_Display_inst
    (
        .clk(clk),
        .RST_N(RST_N),
        .Displayed_number(Displayed_number),
        .Cathode(Cathode),
        .Segment_out(Segment_out)
    );

endmodule

tutorial-2/Seven_Segment_Display_Top_tb.v
`timescale 1ns/1ns
`include "Seven_Segment_Display_Top.v"

module Seven_Segment_Display_Top_tb ();

    // Test signals
    reg clk = 1'b0;
    reg RST_N = 1'b1;
    wire [3:0] Cathode;
    wire [6:0] Segment_out;

    // Instantiate the top module
    Seven_Segment_Display_Top #(
        // Change parameters for simulation purposes, to speed up changes
        .time1(2),
        .startRefreshCounter(0),
        .endRefreshCounter(1)
    ) uut
    (
        .clk(clk),
        .RST_N(RST_N),
        .Cathode(Cathode),
        .Segment_out(Segment_out)
    );

    initial begin
        // Define testbench behaviour
        $dumpfile("Seven_Segment_Display_Top_tb.vcd");
        $dumpvars(0, Seven_Segment_Display_Top_tb);

        // Test conditions
        for (integer i=0; i<100; i=i+1) begin
            // Pulse clock, 20 units per cycle
            clk = ~clk; #10;
        end
        $display("Test completed!");
    end

endmodule

tutorial-2/Seven_Segment_Display_Top_tb.vcd
$date
	Tue Apr 06 00:58:46 2021
$end
$version
	Icarus Verilog
$end
$timescale
	1ns
$end
$scope module Seven_Segment_Display_Top_tb $end
$var wire 7 ! Segment_out [6:0] $end
$var wire 4 " Cathode [3:0] $end
$var reg 1 # RST_N $end
$var reg 1 $ clk $end
$scope module uut $end
$var wire 1 # RST_N $end
$var wire 1 $ clk $end
$var wire 7 % Segment_out [6:0] $end
$var wire 16 & Displayed_number [15:0] $end
$var wire 4 ' Cathode [3:0] $end
$var reg 1 ( clk_slow $end
$var reg 25 ) count [24:0] $end
$scope module Seven_Segment_Display_inst $end
$var wire 1 # RST_N $end
$var wire 1 $ clk $end
$var wire 7 * Segment_out [6:0] $end
$var wire 2 + LED_activating_counter [1:0] $end
$var wire 16 , Displayed_number [15:0] $end
$var reg 4 - Cathode [3:0] $end
$var reg 4 . Digit_number [3:0] $end
$var reg 16 / refresh_counter [15:0] $end
$scope module i2 $end
$var wire 1 $ CLK_IN $end
$var wire 4 0 NUMBER_IN [3:0] $end
$var reg 7 1 OUTPUT [6:0] $end
$upscope $end
$upscope $end
$scope module i1 $end
$var wire 1 ( CLK_IN $end
$var wire 1 # RST_N $end
$var wire 16 2 SEQUENCE [15:0] $end
$var reg 16 3 SEQUENCE_I1 [15:0] $end
$var reg 16 4 SEQUENCE_I2 [15:0] $end
$upscope $end
$upscope $end
$scope begin $ivl_for_loop0 $end
$var integer 32 5 i [31:0] $end
$upscope $end
$upscope $end
$enddefinitions $end
#0
$dumpvars
b0 5
bx 4
bx 3
bx 2
b1 1
bx 0
b1 /
bx .
b1000 -
bx ,
b1 +
b1 *
b1 )
0(
b1000 '
bx &
b1 %
1$
1#
b1000 "
b1 !
$end
#10
0$
b1 5
#20
b10 +
b10 )
b0xxx .
b0xxx 0
b10 /
b100 "
b100 '
b100 -
1$
b10 5
#30
0$
b11 5
#40
b1 &
b1 ,
b1 2
b0 3
b1 4
b11 +
bx .
bx 0
1(
b0 )
b11 /
b10 "
b10 '
b10 -
1$
b100 5
#50
0$
b101 5
#60
b0 +
b1 )
b1 .
b1 0
b100 /
b1 "
b1 '
b1 -
1$
b110 5
#70
0$
b111 5
#80
b1 +
b1001111 !
b1001111 %
b1001111 *
b1001111 1
b0 .
b0 0
b10 )
b101 /
b1000 "
b1000 '
b1000 -
1$
b1000 5
#90
0$
b1001 5
#100
b10 +
0(
b0 )
b1 !
b1 %
b1 *
b1 1
b110 /
b100 "
b100 '
b100 -
1$
b1010 5
#110
0$
b1011 5
#120
b11 +
b1 )
b111 /
b10 "
b10 '
b10 -
1$
b1100 5
#130
0$
b1101 5
#140
b0 +
b10 )
b1 .
b1 0
b1000 /
b1 "
b1 '
b1 -
1$
b1110 5
#150
0$
b1111 5
#160
b1 3
b0 4
b1 +
b1001111 !
b1001111 %
b1001111 *
b1001111 1
b0 .
b0 0
1(
b0 )
b1001 /
b1000 "
b1000 '
b1000 -
1$
b10000 5
#170
0$
b10001 5
#180
b10 +
b1 )
b1 !
b1 %
b1 *
b1 1
b1010 /
b100 "
b100 '
b100 -
1$
b10010 5
#190
0$
b10011 5
#200
b11 +
b10 )
b1011 /
b10 "
b10 '
b10 -
1$
b10100 5
#210
0$
b10101 5
#220
b0 +
0(
b0 )
b1 .
b1 0
b1100 /
b1 "
b1 '
b1 -
1$
b10110 5
#230
0$
b10111 5
#240
b1 +
b1001111 !
b1001111 %
b1001111 *
b1001111 1
b0 .
b0 0
b1 )
b1101 /
b1000 "
b1000 '
b1000 -
1$
b11000 5
#250
0$
b11001 5
#260
b10 +
b10 )
b1 !
b1 %
b1 *
b1 1
b1110 /
b100 "
b100 '
b100 -
1$
b11010 5
#270
0$
b11011 5
#280
b10 &
b10 ,
b10 2
b1 4
b11 +
1(
b0 )
b1111 /
b10 "
b10 '
b10 -
1$
b11100 5
#290
0$
b11101 5
#300
b0 +
b1 )
b10 .
b10 0
b10000 /
b1 "
b1 '
b1 -
1$
b11110 5
#310
0$
b11111 5
#320
b1 +
b10010 !
b10010 %
b10010 *
b10010 1
b0 .
b0 0
b10 )
b10001 /
b1000 "
b1000 '
b1000 -
1$
b100000 5
#330
0$
b100001 5
#340
b10 +
0(
b0 )
b1 !
b1 %
b1 *
b1 1
b10010 /
b100 "
b100 '
b100 -
1$
b100010 5
#350
0$
b100011 5
#360
b11 +
b1 )
b10011 /
b10 "
b10 '
b10 -
1$
b100100 5
#370
0$
b100101 5
#380
b0 +
b10 )
b10 .
b10 0
b10100 /
b1 "
b1 '
b1 -
1$
b100110 5
#390
0$
b100111 5
#400
b11 &
b11 ,
b11 2
b10 3
b1 +
b10010 !
b10010 %
b10010 *
b10010 1
b0 .
b0 0
1(
b0 )
b10101 /
b1000 "
b1000 '
b1000 -
1$
b101000 5
#410
0$
b101001 5
#420
b10 +
b1 )
b1 !
b1 %
b1 *
b1 1
b10110 /
b100 "
b100 '
b100 -
1$
b101010 5
#430
0$
b101011 5
#440
b11 +
b10 )
b10111 /
b10 "
b10 '
b10 -
1$
b101100 5
#450
0$
b101101 5
#460
b0 +
0(
b0 )
b11 .
b11 0
b11000 /
b1 "
b1 '
b1 -
1$
b101110 5
#470
0$
b101111 5
#480
b1 +
b110 !
b110 %
b110 *
b110 1
b0 .
b0 0
b1 )
b11001 /
b1000 "
b1000 '
b1000 -
1$
b110000 5
#490
0$
b110001 5
#500
b10 +
b10 )
b1 !
b1 %
b1 *
b1 1
b11010 /
b100 "
b100 '
b100 -
1$
b110010 5
#510
0$
b110011 5
#520
b101 &
b101 ,
b101 2
b11 3
b10 4
b11 +
1(
b0 )
b11011 /
b10 "
b10 '
b10 -
1$
b110100 5
#530
0$
b110101 5
#540
b0 +
b1 )
b101 .
b101 0
b11100 /
b1 "
b1 '
b1 -
1$
b110110 5
#550
0$
b110111 5
#560
b1 +
b100100 !
b100100 %
b100100 *
b100100 1
b0 .
b0 0
b10 )
b11101 /
b1000 "
b1000 '
b1000 -
1$
b111000 5
#570
0$
b111001 5
#580
b10 +
0(
b0 )
b1 !
b1 %
b1 *
b1 1
b11110 /
b100 "
b100 '
b100 -
1$
b111010 5
#590
0$
b111011 5
#600
b11 +
b1 )
b11111 /
b10 "
b10 '
b10 -
1$
b111100 5
#610
0$
b111101 5
#620
b0 +
b10 )
b101 .
b101 0
b100000 /
b1 "
b1 '
b1 -
1$
b111110 5
#630
0$
b111111 5
#640
b1000 &
b1000 ,
b1000 2
b101 3
b11 4
b1 +
b100100 !
b100100 %
b100100 *
b100100 1
b0 .
b0 0
1(
b0 )
b100001 /
b1000 "
b1000 '
b1000 -
1$
b1000000 5
#650
0$
b1000001 5
#660
b10 +
b1 )
b1 !
b1 %
b1 *
b1 1
b100010 /
b100 "
b100 '
b100 -
1$
b1000010 5
#670
0$
b1000011 5
#680
b11 +
b10 )
b100011 /
b10 "
b10 '
b10 -
1$
b1000100 5
#690
0$
b1000101 5
#700
b0 +
0(
b0 )
b1000 .
b1000 0
b100100 /
b1 "
b1 '
b1 -
1$
b1000110 5
#710
0$
b1000111 5
#720
b1 +
b0 !
b0 %
b0 *
b0 1
b0 .
b0 0
b1 )
b100101 /
b1000 "
b1000 '
b1000 -
1$
b1001000 5
#730
0$
b1001001 5
#740
b10 +
b10 )
b1 !
b1 %
b1 *
b1 1
b100110 /
b100 "
b100 '
b100 -
1$
b1001010 5
#750
0$
b1001011 5
#760
b1101 &
b1101 ,
b1101 2
b1000 3
b101 4
b11 +
1(
b0 )
b100111 /
b10 "
b10 '
b10 -
1$
b1001100 5
#770
0$
b1001101 5
#780
b0 +
b1 )
b1101 .
b1101 0
b101000 /
b1 "
b1 '
b1 -
1$
b1001110 5
#790
0$
b1001111 5
#800
b1 +
b1000010 !
b1000010 %
b1000010 *
b1000010 1
b0 .
b0 0
b10 )
b101001 /
b1000 "
b1000 '
b1000 -
1$
b1010000 5
#810
0$
b1010001 5
#820
b10 +
0(
b0 )
b1 !
b1 %
b1 *
b1 1
b101010 /
b100 "
b100 '
b100 -
1$
b1010010 5
#830
0$
b1010011 5
#840
b11 +
b1 )
b101011 /
b10 "
b10 '
b10 -
1$
b1010100 5
#850
0$
b1010101 5
#860
b0 +
b10 )
b1101 .
b1101 0
b101100 /
b1 "
b1 '
b1 -
1$
b1010110 5
#870
0$
b1010111 5
#880
b10101 &
b10101 ,
b10101 2
b1101 3
b1000 4
b1 +
b1000010 !
b1000010 %
b1000010 *
b1000010 1
b0 .
b0 0
1(
b0 )
b101101 /
b1000 "
b1000 '
b1000 -
1$
b1011000 5
#890
0$
b1011001 5
#900
b10 +
b1 )
b1 !
b1 %
b1 *
b1 1
b101110 /
b100 "
b100 '
b100 -
1$
b1011010 5
#910
0$
b1011011 5
#920
b11 +
b1 .
b1 0
b10 )
b101111 /
b10 "
b10 '
b10 -
1$
b1011100 5
#930
0$
b1011101 5
#940
b0 +
0(
b0 )
b101 .
b101 0
b1001111 !
b1001111 %
b1001111 *
b1001111 1
b110000 /
b1 "
b1 '
b1 -
1$
b1011110 5
#950
0$
b1011111 5
#960
b1 +
b100100 !
b100100 %
b100100 *
b100100 1
b0 .
b0 0
b1 )
b110001 /
b1000 "
b1000 '
b1000 -
1$
b1100000 5
#970
0$
b1100001 5
#980
b10 +
b10 )
b1 !
b1 %
b1 *
b1 1
b110010 /
b100 "
b100 '
b100 -
1$
b1100010 5
#990
0$
b1100011 5
#1000
b1100100 5
