tutorial-4/fifo_memory.v
module fifo_memory (
    input i_Clock,
    input i_Reset,
    input i_Write_En,
    input i_Read_En,
    input  [c_WIDTH:0] i_Data_In,
    output [c_WIDTH:0] o_Data_Out,
    output reg fifo_full,
    output reg fifo_empty,
    output reg fifo_overflow,
    output reg fifo_underflow
    );

    // Internal memory, 7 16-bit wide registers
    parameter c_DEPTH = 7;
    parameter c_WIDTH = 7;
    reg [c_WIDTH:0] memory [0:c_DEPTH];
    reg [c_DEPTH:0]  wraddr = 0;
    reg [c_DEPTH:0]  rdaddr = 0;
    reg [c_WIDTH:0] r_Data_Out;

    // Writing to FIFO
    always @(posedge i_Clock) begin
        if (i_Write_En) begin
            memory[wraddr] <= i_Data_In;

            // Incrementing wraddr pointer
            if ((!fifo_full) || (i_Read_En)) begin
                wraddr <= wraddr + 1'b1;
                fifo_overflow <= 1'b0;
            end
            else
                fifo_overflow <= 1'b1;
        end
    end

    // Reading from FIFO
    always @(posedge i_Clock) begin
        if (i_Read_En) begin
            r_Data_Out <= memory[rdaddr];

            // Incrementing raddr pointer
            if (!fifo_empty) begin
                rdaddr <= rdaddr + 1'b1;
                fifo_underflow <= 1'b0;
            end
            else
                fifo_underflow <= 1'b1;
        end
    end

    assign o_Data_Out = r_Data_Out;

    // Calculating full/empty flags, referenced from zipcpu.com
    wire	[c_DEPTH:0]	dblnext, nxtread;
    assign	dblnext = wraddr + 2;
    assign	nxtread = rdaddr + 1'b1;

    always @(posedge i_Clock, negedge i_Reset)
        // Reset case
        if (!i_Reset)
        begin
            // Reset output flags
            fifo_full <= 1'b0;
            fifo_empty <= 1'b1;
            
            // Reset internal signals
            wraddr <= 0;
            rdaddr <= 0;
            r_Data_Out <= 0;
        end else casez({ i_Write_En, i_Read_En, !fifo_full, !fifo_empty })
        4'b01?1: begin	// A successful read
            fifo_full  <= 1'b0;
            fifo_empty <= (nxtread == wraddr);
        end
        4'b101?: begin	// A successful write
            fifo_full <= (dblnext == rdaddr);
            fifo_empty <= 1'b0;
        end
        4'b11?0: begin	// Successful write, failed read
            fifo_full  <= 1'b0;
            fifo_empty <= 1'b0;
        end
        4'b11?1: begin	// Successful read and write
            fifo_full  <= fifo_full;
            fifo_empty <= 1'b0;
        end
        default: begin end
        endcase
    
endmodule

tutorial-4/fifo_memory_tb.v
`timescale 1ns/1ns
`include "fifo_memory.v"

module fifo_memory_tb ();
    
    // Test signals
    reg r_Clock = 0;
    reg r_Reset = 1;
    reg r_Write_En = 0;
    reg r_Read_En = 0;
    reg  [15:0] r_Data_In = 0;
    wire [15:0] w_Data_Out;
    wire w_fifo_full;
    wire w_fifo_empty;
    wire w_fifo_overflow;
    wire w_fifo_underflow;

    parameter c_CLOCK_PERIOD_NS = 10;


    // Instantiate module
    fifo_memory #(
        .c_DEPTH(7),
        .c_WIDTH(15)
    ) UUT (
        .i_Clock(r_Clock),
        .i_Reset(r_Reset),
        .i_Write_En(r_Write_En),
        .i_Read_En(r_Read_En),
        .i_Data_In(r_Data_In),
        .o_Data_Out(w_Data_Out),
        .fifo_full(w_fifo_full),
        .fifo_empty(w_fifo_empty),
        .fifo_overflow(w_fifo_overflow),
        .fifo_underflow(w_fifo_underflow)
        );

    // Testbench logic
    always
        #(c_CLOCK_PERIOD_NS/2) r_Clock <= !r_Clock;

    // Main Testing:
    initial
    begin
        // Initialise module through reset
        r_Reset = ~r_Reset;
        #10
        r_Reset = ~r_Reset;
        #10

        // Write two bytes
        r_Data_In  <= 16'hBEEF;
        r_Write_En <= 1'b1;
        #10;
        r_Write_En <= 1'b0;
        r_Read_En  <= 1'b1;
        #10
        // Check that the correct data was received
        if (w_Data_Out == 16'hBEEF)
        $display("Test Passed - Correct two bytes received");
        else
        $display("Test Failed - Incorrect two bytes received");
        

        // Try overflowing it
        r_Write_En <= 1'b0;
        r_Read_En  <= 1'b0;

        for (integer i = 16'h0; i < 16'h1FF; i = i + 1'b1) begin
            r_Data_In  <= i;
            r_Write_En <= 1'b1;
            #10;
        end
        r_Write_En <= 1'b0;
        r_Read_En  <= 1'b0;
        if (w_fifo_overflow)
        $display("Test Passed - Overflow flag works");
        else
        $display("Test Failed - Overflow flag failed");


        // Try underflowing it
        r_Write_En <= 1'b0;
        r_Read_En  <= 1'b0;

        for (integer i = 16'h0; i < 16'h2FF; i = i + 1'b1) begin
            r_Read_En <= 1'b1;
            #10;
        end
        r_Write_En <= 1'b0;
        r_Read_En  <= 1'b0;
        if (w_fifo_underflow)
        $display("Test Passed - Underflow flag works");
        else
        $display("Test Failed - Underflow flag failed");
        $finish();
    end

    initial 
    begin
    // Required to dump signals
    $dumpfile("dump.vcd");
    $dumpvars(0);
    end

endmodule

tutorial-3/dump.vcd
$date
	Tue Apr 06 17:10:46 2021
$end
$version
	Icarus Verilog
$end
$timescale
	1ns
$end
$scope module fifo_memory_tb $end
$var wire 1 ! w_fifo_underflow $end
$var wire 1 " w_fifo_overflow $end
$var wire 1 # w_fifo_full $end
$var wire 1 $ w_fifo_empty $end
$var wire 16 % w_Data_Out [15:0] $end
$var reg 1 & r_Clock $end
$var reg 16 ' r_Data_In [15:0] $end
$var reg 1 ( r_Read_En $end
$var reg 1 ) r_Reset $end
$var reg 1 * r_Write_En $end
$scope module UUT $end
$var wire 1 & i_Clock $end
$var wire 16 + i_Data_In [15:0] $end
$var wire 1 ( i_Read_En $end
$var wire 1 ) i_Reset $end
$var wire 1 * i_Write_En $end
$var wire 16 , o_Data_Out [15:0] $end
$var wire 8 - nxtread [7:0] $end
$var wire 8 . dblnext [7:0] $end
$var reg 1 $ fifo_empty $end
$var reg 1 # fifo_full $end
$var reg 1 " fifo_overflow $end
$var reg 1 ! fifo_underflow $end
$var reg 16 / r_Data_Out [15:0] $end
$var reg 8 0 rdaddr [7:0] $end
$var reg 8 1 wraddr [7:0] $end
$upscope $end
$scope begin $ivl_for_loop0 $end
$var integer 32 2 i [31:0] $end
$upscope $end
$scope begin $ivl_for_loop1 $end
$var integer 32 3 i [31:0] $end
$upscope $end
$upscope $end
$enddefinitions $end
#0
$dumpvars
bx 3
bx 2
b0 1
b0 0
b0 /
b10 .
b1 -
b0 ,
b0 +
0*
0)
0(
b0 '
0&
b0 %
0$
0#
0"
0!
$end
#5
1$
1&
#10
0&
1)
#15
1&
#20
0&
1*
b1011111011101111 '
b1011111011101111 +
#25
b11 .
b1 1
0$
1&
#30
0&
1(
0*
#35
1$
b10 -
b1 0
b1011111011101111 %
b1011111011101111 ,
b1011111011101111 /
1&
#40
0&
1*
b0 '
b0 +
0(
b0 2
#45
b100 .
b10 1
0$
1&
#50
0&
b1 '
b1 +
b1 2
#55
b101 .
b11 1
1&
#60
0&
b10 '
b10 +
b10 2
#65
b110 .
b100 1
1&
#70
0&
b11 '
b11 +
b11 2
#75
b111 .
b101 1
1&
#80
0&
b100 '
b100 +
b100 2
#85
b1000 .
b110 1
1&
#90
0&
b101 '
b101 +
b101 2
#95
b1001 .
b111 1
1&
#100
0&
b110 '
b110 +
b110 2
#105
b1010 .
b1000 1
1&
#110
0&
b111 '
b111 +
b111 2
#115
b1011 .
b1001 1
1&
#120
0&
b1000 '
b1000 +
b1000 2
#125
b1100 .
b1010 1
1&
#130
0&
b1001 '
b1001 +
b1001 2
#135
b1101 .
b1011 1
1&
#140
0&
b1010 '
b1010 +
b1010 2
#145
b1110 .
b1100 1
1&
#150
0&
b1011 '
b1011 +
b1011 2
#155
b1111 .
b1101 1
1&
#160
0&
b1100 '
b1100 +
b1100 2
#165
b10000 .
b1110 1
1&
#170
0&
b1101 '
b1101 +
b1101 2
#175
b10001 .
b1111 1
1&
#180
0&
b1110 '
b1110 +
b1110 2
#185
b10010 .
b10000 1
1&
#190
0&
b1111 '
b1111 +
b1111 2
#195
b10011 .
b10001 1
1&
#200
0&
b10000 '
b10000 +
b10000 2
#205
b10100 .
b10010 1
1&
#210
0&
b10001 '
b10001 +
b10001 2
#215
b10101 .
b10011 1
1&
#220
0&
b10010 '
b10010 +
b10010 2
#225
b10110 .
b10100 1
1&
#230
0&
b10011 '
b10011 +
b10011 2
#235
b10111 .
b10101 1
1&
#240
0&
b10100 '
b10100 +
b10100 2
#245
b11000 .
b10110 1
1&
#250
0&
b10101 '
b10101 +
b10101 2
#255
b11001 .
b10111 1
1&
#260
0&
b10110 '
b10110 +
b10110 2
#265
b11010 .
b11000 1
1&
#270
0&
b10111 '
b10111 +
b10111 2
#275
b11011 .
b11001 1
1&
#280
0&
b11000 '
b11000 +
b11000 2
#285
b11100 .
b11010 1
1&
#290
0&
b11001 '
b11001 +
b11001 2
#295
b11101 .
b11011 1
1&
#300
0&
b11010 '
b11010 +
b11010 2
#305
b11110 .
b11100 1
1&
#310
0&
b11011 '
b11011 +
b11011 2
#315
b11111 .
b11101 1
1&
#320
0&
b11100 '
b11100 +
b11100 2
#325
b100000 .
b11110 1
1&
#330
0&
b11101 '
b11101 +
b11101 2
#335
b100001 .
b11111 1
1&
#340
0&
b11110 '
b11110 +
b11110 2
#345
b100010 .
b100000 1
1&
#350
0&
b11111 '
b11111 +
b11111 2
#355
b100011 .
b100001 1
1&
#360
0&
b100000 '
b100000 +
b100000 2
#365
b100100 .
b100010 1
1&
#370
0&
b100001 '
b100001 +
b100001 2
#375
b100101 .
b100011 1
1&
#380
0&
b100010 '
b100010 +
b100010 2
#385
b100110 .
b100100 1
1&
#390
0&
b100011 '
b100011 +
b100011 2
#395
b100111 .
b100101 1
1&
#400
0&
b100100 '
b100100 +
b100100 2
#405
b101000 .
b100110 1
1&
#410
0&
b100101 '
b100101 +
b100101 2
#415
b101001 .
b100111 1
1&
#420
0&
b100110 '
b100110 +
b100110 2
#425
b101010 .
b101000 1
1&
#430
0&
b100111 '
b100111 +
b100111 2
#435
b101011 .
b101001 1
1&
#440
0&
b101000 '
b101000 +
b101000 2
#445
b101100 .
b101010 1
1&
#450
0&
b101001 '
b101001 +
b101001 2
#455
b101101 .
b101011 1
1&
#460
0&
b101010 '
b101010 +
b101010 2
#465
b101110 .
b101100 1
1&
#470
0&
b101011 '
b101011 +
b101011 2
#475
b101111 .
b101101 1
1&
#480
0&
b101100 '
b101100 +
b101100 2
#485
b110000 .
b101110 1
1&
#490
0&
b101101 '
b101101 +
b101101 2
#495
b110001 .
b101111 1
1&
#500
0&
b101110 '
b101110 +
b101110 2
#505
b110010 .
b110000 1
1&
#510
0&
b101111 '
b101111 +
b101111 2
#515
b110011 .
b110001 1
1&
#520
0&
b110000 '
b110000 +
b110000 2
#525
b110100 .
b110010 1
1&
#530
0&
b110001 '
b110001 +
b110001 2
#535
b110101 .
b110011 1
1&
#540
0&
b110010 '
b110010 +
b110010 2
#545
b110110 .
b110100 1
1&
#550
0&
b110011 '
b110011 +
b110011 2
#555
b110111 .
b110101 1
1&
#560
0&
b110100 '
b110100 +
b110100 2
#565
b111000 .
b110110 1
1&
#570
0&
b110101 '
b110101 +
b110101 2
#575
b111001 .
b110111 1
1&
#580
0&
b110110 '
b110110 +
b110110 2
#585
b111010 .
b111000 1
1&
#590
0&
b110111 '
b110111 +
b110111 2
#595
b111011 .
b111001 1
1&
#600
0&
b111000 '
b111000 +
b111000 2
#605
b111100 .
b111010 1
1&
#610
0&
b111001 '
b111001 +
b111001 2
#615
b111101 .
b111011 1
1&
#620
0&
b111010 '
b111010 +
b111010 2
#625
b111110 .
b111100 1
1&
#630
0&
b111011 '
b111011 +
b111011 2
#635
b111111 .
b111101 1
1&
#640
0&
b111100 '
b111100 +
b111100 2
#645
b1000000 .
b111110 1
1&
#650
0&
b111101 '
b111101 +
b111101 2
#655
b1000001 .
b111111 1
1&
#660
0&
b111110 '
b111110 +
b111110 2
#665
b1000010 .
b1000000 1
1&
#670
0&
b111111 '
b111111 +
b111111 2
#675
b1000011 .
b1000001 1
1&
#680
0&
b1000000 '
b1000000 +
b1000000 2
#685
b1000100 .
b1000010 1
1&
#690
0&
b1000001 '
b1000001 +
b1000001 2
#695
b1000101 .
b1000011 1
1&
#700
0&
b1000010 '
b1000010 +
b1000010 2
#705
b1000110 .
b1000100 1
1&
#710
0&
b1000011 '
b1000011 +
b1000011 2
#715
b1000111 .
b1000101 1
1&
#720
0&
b1000100 '
b1000100 +
b1000100 2
#725
b1001000 .
b1000110 1
1&
#730
0&
b1000101 '
b1000101 +
b1000101 2
#735
b1001001 .
b1000111 1
1&
#740
0&
b1000110 '
b1000110 +
b1000110 2
#745
b1001010 .
b1001000 1
1&
#750
0&
b1000111 '
b1000111 +
b1000111 2
#755
b1001011 .
b1001001 1
1&
#760
0&
b1001000 '
b1001000 +
b1001000 2
#765
b1001100 .
b1001010 1
1&
#770
0&
b1001001 '
b1001001 +
b1001001 2
#775
b1001101 .
b1001011 1
1&
#780
0&
b1001010 '
b1001010 +
b1001010 2
#785
b1001110 .
b1001100 1
1&
#790
0&
b1001011 '
b1001011 +
b1001011 2
#795
b1001111 .
b1001101 1
1&
#800
0&
b1001100 '
b1001100 +
b1001100 2
#805
b1010000 .
b1001110 1
1&
#810
0&
b1001101 '
b1001101 +
b1001101 2
#815
b1010001 .
b1001111 1
1&
#820
0&
b1001110 '
b1001110 +
b1001110 2
#825
b1010010 .
b1010000 1
1&
#830
0&
b1001111 '
b1001111 +
b1001111 2
#835
b1010011 .
b1010001 1
1&
#840
0&
b1010000 '
b1010000 +
b1010000 2
#845
b1010100 .
b1010010 1
1&
#850
0&
b1010001 '
b1010001 +
b1010001 2
#855
b1010101 .
b1010011 1
1&
#860
0&
b1010010 '
b1010010 +
b1010010 2
#865
b1010110 .
b1010100 1
1&
#870
0&
b1010011 '
b1010011 +
b1010011 2
#875
b1010111 .
b1010101 1
1&
#880
0&
b1010100 '
b1010100 +
b1010100 2
#885
b1011000 .
b1010110 1
1&
#890
0&
b1010101 '
b1010101 +
b1010101 2
#895
b1011001 .
b1010111 1
1&
#900
0&
b1010110 '
b1010110 +
b1010110 2
#905
b1011010 .
b1011000 1
1&
#910
0&
b1010111 '
b1010111 +
b1010111 2
#915
b1011011 .
b1011001 1
1&
#920
0&
b1011000 '
b1011000 +
b1011000 2
#925
b1011100 .
b1011010 1
1&
#930
0&
b1011001 '
b1011001 +
b1011001 2
#935
b1011101 .
b1011011 1
1&
#940
0&
b1011010 '
b1011010 +
b1011010 2
#945
b1011110 .
b1011100 1
1&
#950
0&
b1011011 '
b1011011 +
b1011011 2
#955
b1011111 .
b1011101 1
1&
#960
0&
b1011100 '
b1011100 +
b1011100 2
#965
b1100000 .
b1011110 1
1&
#970
0&
b1011101 '
b1011101 +
b1011101 2
#975
b1100001 .
b1011111 1
1&
#980
0&
b1011110 '
b1011110 +
b1011110 2
#985
b1100010 .
b1100000 1
1&
#990
0&
b1011111 '
b1011111 +
b1011111 2
#995
b1100011 .
b1100001 1
1&
#1000
0&
b1100000 '
b1100000 +
b1100000 2
#1005
b1100100 .
b1100010 1
1&
#1010
0&
b1100001 '
b1100001 +
b1100001 2
#1015
b1100101 .
b1100011 1
1&
#1020
0&
b1100010 '
b1100010 +
b1100010 2
#1025
b1100110 .
b1100100 1
1&
#1030
0&
b1100011 '
b1100011 +
b1100011 2
#1035
b1100111 .
b1100101 1
1&
#1040
0&
b1100100 '
b1100100 +
b1100100 2
#1045
b1101000 .
b1100110 1
1&
#1050
0&
b1100101 '
b1100101 +
b1100101 2
#1055
b1101001 .
b1100111 1
1&
#1060
0&
b1100110 '
b1100110 +
b1100110 2
#1065
b1101010 .
b1101000 1
1&
#1070
0&
b1100111 '
b1100111 +
b1100111 2
#1075
b1101011 .
b1101001 1
1&
#1080
0&
b1101000 '
b1101000 +
b1101000 2
#1085
b1101100 .
b1101010 1
1&
#1090
0&
b1101001 '
b1101001 +
b1101001 2
#1095
b1101101 .
b1101011 1
1&
#1100
0&
b1101010 '
b1101010 +
b1101010 2
#1105
b1101110 .
b1101100 1
1&
#1110
0&
b1101011 '
b1101011 +
b1101011 2
#1115
b1101111 .
b1101101 1
1&
#1120
0&
b1101100 '
b1101100 +
b1101100 2
#1125
b1110000 .
b1101110 1
1&
#1130
0&
b1101101 '
b1101101 +
b1101101 2
#1135
b1110001 .
b1101111 1
1&
#1140
0&
b1101110 '
b1101110 +
b1101110 2
#1145
b1110010 .
b1110000 1
1&
#1150
0&
b1101111 '
b1101111 +
b1101111 2
#1155
b1110011 .
b1110001 1
1&
#1160
0&
b1110000 '
b1110000 +
b1110000 2
#1165
b1110100 .
b1110010 1
1&
#1170
0&
b1110001 '
b1110001 +
b1110001 2
#1175
b1110101 .
b1110011 1
1&
#1180
0&
b1110010 '
b1110010 +
b1110010 2
#1185
b1110110 .
b1110100 1
1&
#1190
0&
b1110011 '
b1110011 +
b1110011 2
#1195
b1110111 .
b1110101 1
1&
#1200
0&
b1110100 '
b1110100 +
b1110100 2
#1205
b1111000 .
b1110110 1
1&
#1210
0&
b1110101 '
b1110101 +
b1110101 2
#1215
b1111001 .
b1110111 1
1&
#1220
0&
b1110110 '
b1110110 +
b1110110 2
#1225
b1111010 .
b1111000 1
1&
#1230
0&
b1110111 '
b1110111 +
b1110111 2
#1235
b1111011 .
b1111001 1
1&
#1240
0&
b1111000 '
b1111000 +
b1111000 2
#1245
b1111100 .
b1111010 1
1&
#1250
0&
b1111001 '
b1111001 +
b1111001 2
#1255
b1111101 .
b1111011 1
1&
#1260
0&
b1111010 '
b1111010 +
b1111010 2
#1265
b1111110 .
b1111100 1
1&
#1270
0&
b1111011 '
b1111011 +
b1111011 2
#1275
b1111111 .
b1111101 1
1&
#1280
0&
b1111100 '
b1111100 +
b1111100 2
#1285
b10000000 .
b1111110 1
1&
#1290
0&
b1111101 '
b1111101 +
b1111101 2
#1295
b10000001 .
b1111111 1
1&
#1300
0&
b1111110 '
b1111110 +
b1111110 2
#1305
b10000010 .
b10000000 1
1&
#1310
0&
b1111111 '
b1111111 +
b1111111 2
#1315
b10000011 .
b10000001 1
1&
#1320
0&
b10000000 '
b10000000 +
b10000000 2
#1325
b10000100 .
b10000010 1
1&
#1330
0&
b10000001 '
b10000001 +
b10000001 2
#1335
b10000101 .
b10000011 1
1&
#1340
0&
b10000010 '
b10000010 +
b10000010 2
#1345
b10000110 .
b10000100 1
1&
#1350
0&
b10000011 '
b10000011 +
b10000011 2
#1355
b10000111 .
b10000101 1
1&
#1360
0&
b10000100 '
b10000100 +
b10000100 2
#1365
b10001000 .
b10000110 1
1&
#1370
0&
b10000101 '
b10000101 +
b10000101 2
#1375
b10001001 .
b10000111 1
1&
#1380
0&
b10000110 '
b10000110 +
b10000110 2
#1385
b10001010 .
b10001000 1
1&
#1390
0&
b10000111 '
b10000111 +
b10000111 2
#1395
b10001011 .
b10001001 1
1&
#1400
0&
b10001000 '
b10001000 +
b10001000 2
#1405
b10001100 .
b10001010 1
1&
#1410
0&
b10001001 '
b10001001 +
b10001001 2
#1415
b10001101 .
b10001011 1
1&
#1420
0&
b10001010 '
b10001010 +
b10001010 2
#1425
b10001110 .
b10001100 1
1&
#1430
0&
b10001011 '
b10001011 +
b10001011 2
#1435
b10001111 .
b10001101 1
1&
#1440
0&
b10001100 '
b10001100 +
b10001100 2
#1445
b10010000 .
b10001110 1
1&
#1450
0&
b10001101 '
b10001101 +
b10001101 2
#1455
b10010001 .
b10001111 1
1&
#1460
0&
b10001110 '
b10001110 +
b10001110 2
#1465
b10010010 .
b10010000 1
1&
#1470
0&
b10001111 '
b10001111 +
b10001111 2
#1475
b10010011 .
b10010001 1
1&
#1480
0&
b10010000 '
b10010000 +
b10010000 2
#1485
b10010100 .
b10010010 1
1&
#1490
0&
b10010001 '
b10010001 +
b10010001 2
#1495
b10010101 .
b10010011 1
1&
#1500
0&
b10010010 '
b10010010 +
b10010010 2
#1505
b10010110 .
b10010100 1
1&
#1510
0&
b10010011 '
b10010011 +
b10010011 2
#1515
b10010111 .
b10010101 1
1&
#1520
0&
b10010100 '
b10010100 +
b10010100 2
#1525
b10011000 .
b10010110 1
1&
#1530
0&
b10010101 '
b10010101 +
b10010101 2
#1535
b10011001 .
b10010111 1
1&
#1540
0&
b10010110 '
b10010110 +
b10010110 2
#1545
b10011010 .
b10011000 1
1&
#1550
0&
b10010111 '
b10010111 +
b10010111 2
#1555
b10011011 .
b10011001 1
1&
#1560
0&
b10011000 '
b10011000 +
b10011000 2
#1565
b10011100 .
b10011010 1
1&
#1570
0&
b10011001 '
b10011001 +
b10011001 2
#1575
b10011101 .
b10011011 1
1&
#1580
0&
b10011010 '
b10011010 +
b10011010 2
#1585
b10011110 .
b10011100 1
1&
#1590
0&
b10011011 '
b10011011 +
b10011011 2
#1595
b10011111 .
b10011101 1
1&
#1600
0&
b10011100 '
b10011100 +
b10011100 2
#1605
b10100000 .
b10011110 1
1&
#1610
0&
b10011101 '
b10011101 +
b10011101 2
#1615
b10100001 .
b10011111 1
1&
#1620
0&
b10011110 '
b10011110 +
b10011110 2
#1625
b10100010 .
b10100000 1
1&
#1630
0&
b10011111 '
b10011111 +
b10011111 2
#1635
b10100011 .
b10100001 1
1&
#1640
0&
b10100000 '
b10100000 +
b10100000 2
#1645
b10100100 .
b10100010 1
1&
#1650
0&
b10100001 '
b10100001 +
b10100001 2
#1655
b10100101 .
b10100011 1
1&
#1660
0&
b10100010 '
b10100010 +
b10100010 2
#1665
b10100110 .
b10100100 1
1&
#1670
0&
b10100011 '
b10100011 +
b10100011 2
#1675
b10100111 .
b10100101 1
1&
#1680
0&
b10100100 '
b10100100 +
b10100100 2
#1685
b10101000 .
b10100110 1
1&
#1690
0&
b10100101 '
b10100101 +
b10100101 2
#1695
b10101001 .
b10100111 1
1&
#1700
0&
b10100110 '
b10100110 +
b10100110 2
#1705
b10101010 .
b10101000 1
1&
#1710
0&
b10100111 '
b10100111 +
b10100111 2
#1715
b10101011 .
b10101001 1
1&
#1720
0&
b10101000 '
b10101000 +
b10101000 2
#1725
b10101100 .
b10101010 1
1&
#1730
0&
b10101001 '
b10101001 +
b10101001 2
#1735
b10101101 .
b10101011 1
1&
#1740
0&
b10101010 '
b10101010 +
b10101010 2
#1745
b10101110 .
b10101100 1
1&
#1750
0&
b10101011 '
b10101011 +
b10101011 2
#1755
b10101111 .
b10101101 1
1&
#1760
0&
b10101100 '
b10101100 +
b10101100 2
#1765
b10110000 .
b10101110 1
1&
#1770
0&
b10101101 '
b10101101 +
b10101101 2
#1775
b10110001 .
b10101111 1
1&
#1780
0&
b10101110 '
b10101110 +
b10101110 2
#1785
b10110010 .
b10110000 1
1&
#1790
0&
b10101111 '
b10101111 +
b10101111 2
#1795
b10110011 .
b10110001 1
1&
#1800
0&
b10110000 '
b10110000 +
b10110000 2
#1805
b10110100 .
b10110010 1
1&
#1810
0&
b10110001 '
b10110001 +
b10110001 2
#1815
b10110101 .
b10110011 1
1&
#1820
0&
b10110010 '
b10110010 +
b10110010 2
#1825
b10110110 .
b10110100 1
1&
#1830
0&
b10110011 '
b10110011 +
b10110011 2
#1835
b10110111 .
b10110101 1
1&
#1840
0&
b10110100 '
b10110100 +
b10110100 2
#1845
b10111000 .
b10110110 1
1&
#1850
0&
b10110101 '
b10110101 +
b10110101 2
#1855
b10111001 .
b10110111 1
1&
#1860
0&
b10110110 '
b10110110 +
b10110110 2
#1865
b10111010 .
b10111000 1
1&
#1870
0&
b10110111 '
b10110111 +
b10110111 2
#1875
b10111011 .
b10111001 1
1&
#1880
0&
b10111000 '
b10111000 +
b10111000 2
#1885
b10111100 .
b10111010 1
1&
#1890
0&
b10111001 '
b10111001 +
b10111001 2
#1895
b10111101 .
b10111011 1
1&
#1900
0&
b10111010 '
b10111010 +
b10111010 2
#1905
b10111110 .
b10111100 1
1&
#1910
0&
b10111011 '
b10111011 +
b10111011 2
#1915
b10111111 .
b10111101 1
1&
#1920
0&
b10111100 '
b10111100 +
b10111100 2
#1925
b11000000 .
b10111110 1
1&
#1930
0&
b10111101 '
b10111101 +
b10111101 2
#1935
b11000001 .
b10111111 1
1&
#1940
0&
b10111110 '
b10111110 +
b10111110 2
#1945
b11000010 .
b11000000 1
1&
#1950
0&
b10111111 '
b10111111 +
b10111111 2
#1955
b11000011 .
b11000001 1
1&
#1960
0&
b11000000 '
b11000000 +
b11000000 2
#1965
b11000100 .
b11000010 1
1&
#1970
0&
b11000001 '
b11000001 +
b11000001 2
#1975
b11000101 .
b11000011 1
1&
#1980
0&
b11000010 '
b11000010 +
b11000010 2
#1985
b11000110 .
b11000100 1
1&
#1990
0&
b11000011 '
b11000011 +
b11000011 2
#1995
b11000111 .
b11000101 1
1&
#2000
0&
b11000100 '
b11000100 +
b11000100 2
#2005
b11001000 .
b11000110 1
1&
#2010
0&
b11000101 '
b11000101 +
b11000101 2
#2015
b11001001 .
b11000111 1
1&
#2020
0&
b11000110 '
b11000110 +
b11000110 2
#2025
b11001010 .
b11001000 1
1&
#2030
0&
b11000111 '
b11000111 +
b11000111 2
#2035
b11001011 .
b11001001 1
1&
#2040
0&
b11001000 '
b11001000 +
b11001000 2
#2045
b11001100 .
b11001010 1
1&
#2050
0&
b11001001 '
b11001001 +
b11001001 2
#2055
b11001101 .
b11001011 1
1&
#2060
0&
b11001010 '
b11001010 +
b11001010 2
#2065
b11001110 .
b11001100 1
1&
#2070
0&
b11001011 '
b11001011 +
b11001011 2
#2075
b11001111 .
b11001101 1
1&
#2080
0&
b11001100 '
b11001100 +
b11001100 2
#2085
b11010000 .
b11001110 1
1&
#2090
0&
b11001101 '
b11001101 +
b11001101 2
#2095
b11010001 .
b11001111 1
1&
#2100
0&
b11001110 '
b11001110 +
b11001110 2
#2105
b11010010 .
b11010000 1
1&
#2110
0&
b11001111 '
b11001111 +
b11001111 2
#2115
b11010011 .
b11010001 1
1&
#2120
0&
b11010000 '
b11010000 +
b11010000 2
#2125
b11010100 .
b11010010 1
1&
#2130
0&
b11010001 '
b11010001 +
b11010001 2
#2135
b11010101 .
b11010011 1
1&
#2140
0&
b11010010 '
b11010010 +
b11010010 2
#2145
b11010110 .
b11010100 1
1&
#2150
0&
b11010011 '
b11010011 +
b11010011 2
#2155
b11010111 .
b11010101 1
1&
#2160
0&
b11010100 '
b11010100 +
b11010100 2
#2165
b11011000 .
b11010110 1
1&
#2170
0&
b11010101 '
b11010101 +
b11010101 2
#2175
b11011001 .
b11010111 1
1&
#2180
0&
b11010110 '
b11010110 +
b11010110 2
#2185
b11011010 .
b11011000 1
1&
#2190
0&
b11010111 '
b11010111 +
b11010111 2
#2195
b11011011 .
b11011001 1
1&
#2200
0&
b11011000 '
b11011000 +
b11011000 2
#2205
b11011100 .
b11011010 1
1&
#2210
0&
b11011001 '
b11011001 +
b11011001 2
#2215
b11011101 .
b11011011 1
1&
#2220
0&
b11011010 '
b11011010 +
b11011010 2
#2225
b11011110 .
b11011100 1
1&
#2230
0&
b11011011 '
b11011011 +
b11011011 2
#2235
b11011111 .
b11011101 1
1&
#2240
0&
b11011100 '
b11011100 +
b11011100 2
#2245
b11100000 .
b11011110 1
1&
#2250
0&
b11011101 '
b11011101 +
b11011101 2
#2255
b11100001 .
b11011111 1
1&
#2260
0&
b11011110 '
b11011110 +
b11011110 2
#2265
b11100010 .
b11100000 1
1&
#2270
0&
b11011111 '
b11011111 +
b11011111 2
#2275
b11100011 .
b11100001 1
1&
#2280
0&
b11100000 '
b11100000 +
b11100000 2
#2285
b11100100 .
b11100010 1
1&
#2290
0&
b11100001 '
b11100001 +
b11100001 2
#2295
b11100101 .
b11100011 1
1&
#2300
0&
b11100010 '
b11100010 +
b11100010 2
#2305
b11100110 .
b11100100 1
1&
#2310
0&
b11100011 '
b11100011 +
b11100011 2
#2315
b11100111 .
b11100101 1
1&
#2320
0&
b11100100 '
b11100100 +
b11100100 2
#2325
b11101000 .
b11100110 1
1&
#2330
0&
b11100101 '
b11100101 +
b11100101 2
#2335
b11101001 .
b11100111 1
1&
#2340
0&
b11100110 '
b11100110 +
b11100110 2
#2345
b11101010 .
b11101000 1
1&
#2350
0&
b11100111 '
b11100111 +
b11100111 2
#2355
b11101011 .
b11101001 1
1&
#2360
0&
b11101000 '
b11101000 +
b11101000 2
#2365
b11101100 .
b11101010 1
1&
#2370
0&
b11101001 '
b11101001 +
b11101001 2
#2375
b11101101 .
b11101011 1
1&
#2380
0&
b11101010 '
b11101010 +
b11101010 2
#2385
b11101110 .
b11101100 1
1&
#2390
0&
b11101011 '
b11101011 +
b11101011 2
#2395
b11101111 .
b11101101 1
1&
#2400
0&
b11101100 '
b11101100 +
b11101100 2
#2405
b11110000 .
b11101110 1
1&
#2410
0&
b11101101 '
b11101101 +
b11101101 2
#2415
b11110001 .
b11101111 1
1&
#2420
0&
b11101110 '
b11101110 +
b11101110 2
#2425
b11110010 .
b11110000 1
1&
#2430
0&
b11101111 '
b11101111 +
b11101111 2
#2435
b11110011 .
b11110001 1
1&
#2440
0&
b11110000 '
b11110000 +
b11110000 2
#2445
b11110100 .
b11110010 1
1&
#2450
0&
b11110001 '
b11110001 +
b11110001 2
#2455
b11110101 .
b11110011 1
1&
#2460
0&
b11110010 '
b11110010 +
b11110010 2
#2465
b11110110 .
b11110100 1
1&
#2470
0&
b11110011 '
b11110011 +
b11110011 2
#2475
b11110111 .
b11110101 1
1&
#2480
0&
b11110100 '
b11110100 +
b11110100 2
#2485
b11111000 .
b11110110 1
1&
#2490
0&
b11110101 '
b11110101 +
b11110101 2
#2495
b11111001 .
b11110111 1
1&
#2500
0&
b11110110 '
b11110110 +
b11110110 2
#2505
b11111010 .
b11111000 1
1&
#2510
0&
b11110111 '
b11110111 +
b11110111 2
#2515
b11111011 .
b11111001 1
1&
#2520
0&
b11111000 '
b11111000 +
b11111000 2
#2525
b11111100 .
b11111010 1
1&
#2530
0&
b11111001 '
b11111001 +
b11111001 2
