tutorial-3/UART_TX.v
//////////////////////////////////////////////////////////////////////
// File Downloaded from http://www.nandland.com
//////////////////////////////////////////////////////////////////////
// This file contains the UART Transmitter.  This transmitter is able
// to transmit 8 bits of serial data, one start bit, one stop bit,
// and no parity bit.  When transmit is complete o_Tx_done will be
// driven high for one clock cycle.
//
// Set Parameter CLKS_PER_BIT as follows:
// CLKS_PER_BIT = (Frequency of i_Clock)/(Frequency of UART)
// Example: 24 MHz Clock, 115200 baud UART
// (24000000)/(115200) = 208
 
module UART_TX 
  #(parameter CLKS_PER_BIT = 208)
  (
   input       i_Clock,
   input       i_Reset,
   input       i_TX_DV,
   input [7:0] i_TX_Byte, 
   output      o_TX_Active,
   output reg  o_TX_Serial,
   output      o_TX_Done
   );
 
  parameter IDLE         = 3'b000;
  parameter TX_START_BIT = 3'b001;
  parameter TX_DATA_BITS = 3'b010;
  parameter TX_STOP_BIT  = 3'b011;
  parameter CLEANUP      = 3'b100;
  
  reg [2:0] r_SM_Main     = 0;
  reg [7:0] r_Clock_Count = 0;
  reg [2:0] r_Bit_Index   = 0;
  reg [7:0] r_TX_Data     = 0;
  reg       r_TX_Done     = 0;
  reg       r_TX_Active   = 0;
    
  always @(posedge i_Clock, negedge i_Reset)
  begin
    if (!i_Reset) begin
        r_SM_Main <= IDLE;
    end
    case (r_SM_Main)
      IDLE :
        begin
          o_TX_Serial   <= 1'b1;         // Drive Line High for Idle
          r_TX_Done     <= 1'b0;
          r_Clock_Count <= 0;
          r_Bit_Index   <= 0;
          
          if (i_TX_DV == 1'b1)
          begin
            r_TX_Active <= 1'b1;
            r_TX_Data   <= i_TX_Byte;
            r_SM_Main   <= TX_START_BIT;
          end
          else
            r_SM_Main <= IDLE;
        end // case: IDLE
      
      
      // Send out Start Bit. Start bit = 0
      TX_START_BIT :
        begin
          o_TX_Serial <= 1'b0;
          
          // Wait CLKS_PER_BIT-1 clock cycles for start bit to finish
          if (r_Clock_Count < CLKS_PER_BIT-1)
          begin
            r_Clock_Count <= r_Clock_Count + 1;
            r_SM_Main     <= TX_START_BIT;
          end
          else
          begin
            r_Clock_Count <= 0;
            r_SM_Main     <= TX_DATA_BITS;
          end
        end // case: TX_START_BIT
      
      
      // Wait CLKS_PER_BIT-1 clock cycles for data bits to finish         
      TX_DATA_BITS :
        begin
          o_TX_Serial <= r_TX_Data[r_Bit_Index];
          
          if (r_Clock_Count < CLKS_PER_BIT-1)
          begin
            r_Clock_Count <= r_Clock_Count + 1;
            r_SM_Main     <= TX_DATA_BITS;
          end
          else
          begin
            r_Clock_Count <= 0;
            
            // Check if we have sent out all bits
            if (r_Bit_Index < 7)
            begin
              r_Bit_Index <= r_Bit_Index + 1;
              r_SM_Main   <= TX_DATA_BITS;
            end
            else
            begin
              r_Bit_Index <= 0;
              r_SM_Main   <= TX_STOP_BIT;
            end
          end 
        end // case: TX_DATA_BITS
      
      
      // Send out Stop bit.  Stop bit = 1
      TX_STOP_BIT :
        begin
          o_TX_Serial <= 1'b1;
          
          // Wait CLKS_PER_BIT-1 clock cycles for Stop bit to finish
          if (r_Clock_Count < CLKS_PER_BIT-1)
          begin
            r_Clock_Count <= r_Clock_Count + 1;
            r_SM_Main     <= TX_STOP_BIT;
          end
          else
          begin
            r_TX_Done     <= 1'b1;
            r_Clock_Count <= 0;
            r_SM_Main     <= CLEANUP;
            r_TX_Active   <= 1'b0;
          end 
        end // case: TX_STOP_BIT
      
      
      // Stay here 1 clock
      CLEANUP :
        begin
          r_TX_Done <= 1'b1;
          r_SM_Main <= IDLE;
        end
      
      
      default :
        r_SM_Main <= IDLE;
      
    endcase
  end
  
  assign o_TX_Active = r_TX_Active;
  assign o_TX_Done   = r_TX_Done;
  
endmodule

tutorial-4/lower_to_upper.v
module lower_to_upper (
    input i_Clock,
    input i_Reset,
    input i_Data_Empty,
    input [7:0] i_data,
    output [7:0] o_data,
    output o_write_enable,
    output o_read_enable
    );

    // Internal registers
    reg r_read_enable;
    reg r_read_en_delay;

    // Shift register to delay one clock cycle
    always @(posedge i_Clock) begin
        r_read_en_delay <= o_write_enable;
        r_read_enable <= r_read_en_delay;
    end

    // Outputs
    assign o_write_enable = ~i_Data_Empty;
    assign o_read_enable = r_read_enable;
    assign o_data = i_data - 8'h20;
    
endmodule

tutorial-4/fifo_memory.v
module fifo_memory (
    input i_Clock,
    input i_Reset,
    input i_Write_En,
    input i_Read_En,
    input  [c_WIDTH:0] i_Data_In,
    output [c_WIDTH:0] o_Data_Out,
    output reg fifo_full,
    output reg fifo_empty,
    output reg fifo_overflow,
    output reg fifo_underflow
    );

    // Internal memory, 7 16-bit wide registers
    parameter c_DEPTH = 7;
    parameter c_WIDTH = 7;
    reg [c_WIDTH:0] memory [0:c_DEPTH];
    reg [c_DEPTH:0]  wraddr = 0;
    reg [c_DEPTH:0]  rdaddr = 0;
    reg [c_WIDTH:0] r_Data_Out;

    // Writing to FIFO
    always @(posedge i_Clock) begin
        if (i_Write_En) begin
            memory[wraddr] <= i_Data_In;

            // Incrementing wraddr pointer
            if ((!fifo_full) || (i_Read_En)) begin
                wraddr <= wraddr + 1'b1;
                fifo_overflow <= 1'b0;
            end
            else
                fifo_overflow <= 1'b1;
        end
    end

    // Reading from FIFO
    always @(posedge i_Clock) begin
        if (i_Read_En) begin
            r_Data_Out <= memory[rdaddr];

            // Incrementing raddr pointer
            if (!fifo_empty) begin
                rdaddr <= rdaddr + 1'b1;
                fifo_underflow <= 1'b0;
            end
            else
                fifo_underflow <= 1'b1;
        end
    end

    assign o_Data_Out = r_Data_Out;

    // Calculating full/empty flags, referenced from zipcpu.com
    wire	[c_DEPTH:0]	dblnext, nxtread;
    assign	dblnext = wraddr + 2;
    assign	nxtread = rdaddr + 1'b1;

    always @(posedge i_Clock, negedge i_Reset)
        // Reset case
        if (!i_Reset)
        begin
            // Reset output flags
            fifo_full <= 1'b0;
            fifo_empty <= 1'b1;
            
            // Reset internal signals
            wraddr <= 0;
            rdaddr <= 0;
            r_Data_Out <= 0;
        end else casez({ i_Write_En, i_Read_En, !fifo_full, !fifo_empty })
        4'b01?1: begin	// A successful read
            fifo_full  <= 1'b0;
            fifo_empty <= (nxtread == wraddr);
        end
        4'b101?: begin	// A successful write
            fifo_full <= (dblnext == rdaddr);
            fifo_empty <= 1'b0;
        end
        4'b11?0: begin	// Successful write, failed read
            fifo_full  <= 1'b0;
            fifo_empty <= 1'b0;
        end
        4'b11?1: begin	// Successful read and write
            fifo_full  <= fifo_full;
            fifo_empty <= 1'b0;
        end
        default: begin end
        endcase
    
endmodule

tutorial-3/UART_RX.v
/////////////////////////////////////////////////////////////////////
// File Downloaded from http://www.nandland.com
/////////////////////////////////////////////////////////////////////
// This file contains the UART Receiver.  This receiver is able to
// receive 8 bits of serial data, one start bit, one stop bit,
// and no parity bit.  When receive is complete o_rx_dv will be
// driven high for one clock cycle.
// 
// Set Parameter CLKS_PER_BIT as follows:
// CLKS_PER_BIT = (Frequency of i_Clock)/(Frequency of UART)
// Example: 24 MHz Clock, 115200 baud UART
// (24000000)/(115200) = 208
 
module UART_RX
  #(parameter CLKS_PER_BIT = 208)
  (
   input        i_Clock,
   input        i_Reset,
   input        i_RX_Serial,
   output       o_RX_Data_Valid,
   output [7:0] o_RX_Byte
   );
   
  parameter IDLE         = 3'b000;
  parameter RX_START_BIT = 3'b001;
  parameter RX_DATA_BITS = 3'b010;
  parameter RX_STOP_BIT  = 3'b011;
  parameter CLEANUP      = 3'b100;
  
  reg [7:0]     r_Clock_Count   = 0;
  reg [2:0]     r_Bit_Index     = 0; //8 bits total
  reg [7:0]     r_RX_Byte       = 0;
  reg           o_RX_Data_Valid = 0;
  reg [2:0]     r_SM_Main       = 0;
  
  
  // Purpose: Control RX state machine
  always @(posedge i_Clock, negedge i_Reset)
  begin
    if (!i_Reset) begin
        o_RX_Data_Valid   <= 1'b0;
        r_Clock_Count     <= 0;
        r_Bit_Index       <= 0;
        r_SM_Main         <= IDLE;
    end
    case (r_SM_Main)
      IDLE :
        begin
          o_RX_Data_Valid   <= 1'b0;
          r_Clock_Count     <= 0;
          r_Bit_Index       <= 0;
          
          if (i_RX_Serial == 1'b0)          // Start bit detected
            r_SM_Main <= RX_START_BIT;
          else
            r_SM_Main <= IDLE;
        end
      
      // Check middle of start bit to make sure it's still low
      RX_START_BIT :
        begin
          if (r_Clock_Count == (CLKS_PER_BIT-1)/2)
          begin
            if (i_RX_Serial == 1'b0)
            begin
              r_Clock_Count <= 0;  // reset counter, found the middle
              r_SM_Main     <= RX_DATA_BITS;
            end
            else
              r_SM_Main <= IDLE;
          end
          else
          begin
            r_Clock_Count <= r_Clock_Count + 1;
            r_SM_Main     <= RX_START_BIT;
          end
        end // case: RX_START_BIT
      
      
      // Wait CLKS_PER_BIT-1 clock cycles to sample serial data
      RX_DATA_BITS :
        begin
          if (r_Clock_Count < CLKS_PER_BIT-1)
          begin
            r_Clock_Count <= r_Clock_Count + 1;
            r_SM_Main     <= RX_DATA_BITS;
          end
          else
          begin
            r_Clock_Count          <= 0;
            r_RX_Byte[r_Bit_Index] <= i_RX_Serial;
            
            // Check if we have received all bits
            if (r_Bit_Index < 7)
            begin
              r_Bit_Index <= r_Bit_Index + 1;
              r_SM_Main   <= RX_DATA_BITS;
            end
            else
            begin
              r_Bit_Index <= 0;
              r_SM_Main   <= RX_STOP_BIT;
            end
          end
        end // case: RX_DATA_BITS
      
      
      // Receive Stop bit.  Stop bit = 1
      RX_STOP_BIT :
        begin
          // Wait CLKS_PER_BIT-1 clock cycles for Stop bit to finish
          if (r_Clock_Count < CLKS_PER_BIT-1)
          begin
            r_Clock_Count <= r_Clock_Count + 1;
     	    r_SM_Main     <= RX_STOP_BIT;
          end
          else
          begin
       	    o_RX_Data_Valid <= 1'b1;
            r_Clock_Count   <= 0;
            r_SM_Main       <= CLEANUP;
          end
        end // case: RX_STOP_BIT
      
      
      // Stay here 1 clock
      CLEANUP :
        begin
          r_SM_Main         <= IDLE;
          o_RX_Data_Valid   <= 1'b0;
        end
      
      
      default :
        r_SM_Main <= IDLE;
      
    endcase
  end    
  
  assign o_RX_DV   = o_RX_Data_Valid;
  assign o_RX_Byte = r_RX_Byte;
  
endmodule // UART_RX

tutorial-4/UART_Transceiver.v
`include "UART_RX.v"
`include "UART_TX.v"
`include "fifo_memory.v"
`include "lower_to_upper.v"

module UART_Transceiver (
    input i_Clock,
    input i_Reset,
    input i_RX_Serial,
    output o_TX_Serial,
    output o_TX_Done
    );
    
    // Board uses a 24 MHz clock
    // Want to interface to 115200 baud UART
    // 24000000 / 115200 = 208 Clocks Per Bit.
    parameter CLOCK_PERIOD_NS = 41;
    parameter CLKS_PER_BIT    = 208;
    parameter BIT_PERIOD      = 8600;
    parameter FIFO_DEPTH      = 7;
    parameter FIFO_WIDTH      = 7;

    // UART RX signals
    wire UART_RX_Data_Valid;
    wire [7:0] UART_RX_Byte;

    // UART_RX instance
    UART_RX #(.CLKS_PER_BIT(CLKS_PER_BIT)) UART_RX_INST
       (.i_Clock(i_Clock),
        .i_Reset(i_Reset),
        .i_RX_Serial(i_RX_Serial),
        .o_RX_Data_Valid(UART_RX_Data_Valid),
        .o_RX_Byte(UART_RX_Byte)
        );

    // FIFO signals
    wire fifo_Write_En;
    wire fifo_Read_En;
    wire [7:0] fifo_Data_In;
    wire [7:0] fifo_Data_Out;
    wire fifo_full;
    wire fifo_empty;
    wire fifo_overflow;
    wire fifo_underflow;

    assign fifo_Data_In  = UART_RX_Byte;
    assign fifo_Write_En = UART_RX_Data_Valid ? 1'b1 : 1'b0;
    assign fifo_Read_En = l2u_write_enable;


    // FIFO instance
    fifo_memory #(
        .c_DEPTH(FIFO_DEPTH),
        .c_WIDTH(FIFO_WIDTH)
    ) fifo_memory_instance (
        .i_Clock(i_Clock),
        .i_Reset(i_Reset),
        .i_Write_En(fifo_Write_En),
        .i_Read_En(fifo_Read_En),
        .i_Data_In(fifo_Data_In),
        .o_Data_Out(fifo_Data_Out),
        .fifo_full(fifo_full),
        .fifo_empty(fifo_empty),
        .fifo_overflow(fifo_overflow),
        .fifo_underflow(fifo_underflow)
        );

    // Lower to Upper signals
    wire [7:0] l2u_data_in;
    wire [7:0] l2u_data_out;
    wire l2u_write_enable;
    wire l2u_read_enable;

    assign l2u_data_in      = fifo_Data_Out;

    // Lower to Upper instance
    lower_to_upper lower_to_upper_instance(
        .i_Clock(i_Clock),
        .i_Reset(i_Reset),
        .i_Data_Empty(fifo_empty),
        .i_data(l2u_data_in),
        .o_data(l2u_data_out),
        .o_write_enable(l2u_write_enable),
        .o_read_enable(l2u_read_enable)
        );

    // UART TX signals
    wire UART_TX_DV;
    wire [7:0] UART_TX_Byte;
    wire UART_TX_Active;

    // Check if data is ready to be read from l2u
    assign UART_TX_Byte = l2u_data_out;
    assign UART_TX_DV = l2u_read_enable;

    // UART TX instance
    UART_TX #(
        .CLKS_PER_BIT(CLKS_PER_BIT)
    ) UART_TX_Inst (
        .i_Clock(i_Clock),
        .i_Reset(i_Reset),
        .i_TX_DV(UART_TX_DV),
        .i_TX_Byte(UART_TX_Byte),
        .o_TX_Active(UART_TX_Active),
        .o_TX_Serial(o_TX_Serial),
        .o_TX_Done(o_TX_Done)
        );

endmodule

tutorial-4/UART_Transceiver_tb.v
`include "UART_Transceiver.v"
`timescale 1ps/1ps

module UART_Transceiver_tb();
    // Test signals
    reg r_Clock;
    reg r_Reset;
    reg r_RX_Serial;
    wire w_TX_Serial;
    wire w_TX_Done;

    // Testbench signals
    wire w_RX_Byte;
    reg  r_RX_Byte;
    reg [7:0] r_Task_UART_Read_DATA = 8'b0;
    reg r_Task_UART_Read_START = 1;
    reg r_Task_UART_Read_STOP = 0;

    parameter c_CLOCK_PERIOD_NS = 40; //40
    parameter c_CLKS_PER_BIT    = 208; //208
    parameter c_BIT_PERIOD      = 8600; //8600
    parameter c_FIFO_DEPTH      = 7;
    parameter c_FIFO_WIDTH      = 7;

    // Instantiate top module
    UART_Transceiver UUT (
        .i_Clock(r_Clock),
        .i_Reset(r_Reset),
        .i_RX_Serial(r_RX_Serial),
        .o_TX_Serial(w_TX_Serial),
        .o_TX_Done(w_TX_Done)
        );

    // Takes in input byte and serializes it 
    task UART_WRITE_BYTE;
    input [7:0] i_Data;
    integer     ii;
    begin
        // Send Start Bit
        r_RX_Serial <= 1'b0;
        #(c_BIT_PERIOD);
        #(c_BIT_PERIOD/8);
        
        // Send Data Byte
        for (ii=0; ii<8; ii=ii+1)
        begin
            r_RX_Serial <= i_Data[ii];
            #(c_BIT_PERIOD);
        end
        
        // Send Stop Bit
        r_RX_Serial <= 1'b1;
        #(c_BIT_PERIOD);
        end
    endtask // UART_WRITE_BYTE

    // Takes in input UART and deserializes it 
    task UART_READ_BYTE;
    integer     iii;
    begin
        // Read Start Bit
        r_Task_UART_Read_START <= w_TX_Serial;
        // #(c_BIT_PERIOD);
        #1000;
        
        // Read Data Byte
        for (iii=0; iii<8; iii=iii+1)
        begin
            r_Task_UART_Read_DATA[iii] <= w_TX_Serial;
            #(c_BIT_PERIOD);
        end
        
        // Read Stop Bit
        r_Task_UART_Read_STOP <= w_TX_Serial;
        #(c_BIT_PERIOD);
        end


    endtask // UART_READ_BYTE

    always #(c_CLOCK_PERIOD_NS/2) r_Clock <= !r_Clock;

    initial begin
        r_Task_UART_Read_START = 0;
        r_Task_UART_Read_STOP  = 0;
        r_Task_UART_Read_DATA  = 8'b0;
        r_RX_Serial = 1;
        r_Reset = 1;
        r_Clock = 0;

        // Initialise module through reset
        r_Reset = ~r_Reset;
        @(posedge r_Clock);
        r_Reset = ~r_Reset;
        @(posedge r_Clock);
        
        // Send a command to the UART (exercise Rx)
        @(posedge r_Clock);
        UART_WRITE_BYTE(8'h61); // 'a' in ASCII
        @(posedge r_Clock);
            
        // Check that the correct command was received
        @(posedge r_Clock);
        UART_READ_BYTE();
        @(posedge r_Clock);
        if (r_Task_UART_Read_DATA == 8'h41) // 'A' in ASCII
        $display("Test Passed - Correct Byte Received");
        else
        $display("Test Failed - Incorrect Byte Received, 0x%0h",r_Task_UART_Read_DATA);

        $finish();
    end

  
    initial 
    begin
        // Required to dump signals
        $dumpfile("dump.vcd");
        $dumpvars(0);
    end


endmodule

tutorial-4/dump.vcd
$date
	Wed Apr 07 13:21:17 2021
$end
$version
	Icarus Verilog
$end
$timescale
	1ps
$end
$scope module UART_Transceiver_tb $end
$var wire 1 ! w_TX_Serial $end
$var wire 1 " w_TX_Done $end
$var reg 1 # r_Clock $end
$var reg 1 $ r_RX_Serial $end
$var reg 1 % r_Reset $end
$var reg 8 & r_Task_UART_Read_DATA [7:0] $end
$var reg 1 ' r_Task_UART_Read_START $end
$var reg 1 ( r_Task_UART_Read_STOP $end
$scope module UUT $end
$var wire 8 ) UART_TX_Byte [7:0] $end
$var wire 1 * UART_TX_DV $end
$var wire 8 + fifo_Data_In [7:0] $end
$var wire 1 , fifo_Read_En $end
$var wire 1 # i_Clock $end
$var wire 1 $ i_RX_Serial $end
$var wire 1 % i_Reset $end
$var wire 8 - l2u_data_in [7:0] $end
$var wire 1 ! o_TX_Serial $end
$var wire 1 " o_TX_Done $end
$var wire 1 . l2u_write_enable $end
$var wire 1 / l2u_read_enable $end
$var wire 8 0 l2u_data_out [7:0] $end
$var wire 1 1 fifo_underflow $end
$var wire 1 2 fifo_overflow $end
$var wire 1 3 fifo_full $end
$var wire 1 4 fifo_empty $end
$var wire 1 5 fifo_Write_En $end
$var wire 8 6 fifo_Data_Out [7:0] $end
$var wire 1 7 UART_TX_Active $end
$var wire 1 8 UART_RX_Data_Valid $end
$var wire 8 9 UART_RX_Byte [7:0] $end
$scope module UART_RX_INST $end
$var wire 1 # i_Clock $end
$var wire 1 $ i_RX_Serial $end
$var wire 1 % i_Reset $end
$var wire 1 : o_RX_DV $end
$var wire 8 ; o_RX_Byte [7:0] $end
$var reg 1 8 o_RX_Data_Valid $end
$var reg 3 < r_Bit_Index [2:0] $end
$var reg 8 = r_Clock_Count [7:0] $end
$var reg 8 > r_RX_Byte [7:0] $end
$var reg 3 ? r_SM_Main [2:0] $end
$upscope $end
$scope module UART_TX_Inst $end
$var wire 1 # i_Clock $end
$var wire 1 % i_Reset $end
$var wire 8 @ i_TX_Byte [7:0] $end
$var wire 1 * i_TX_DV $end
$var wire 1 7 o_TX_Active $end
$var wire 1 " o_TX_Done $end
$var reg 1 ! o_TX_Serial $end
$var reg 3 A r_Bit_Index [2:0] $end
$var reg 8 B r_Clock_Count [7:0] $end
$var reg 3 C r_SM_Main [2:0] $end
$var reg 1 D r_TX_Active $end
$var reg 8 E r_TX_Data [7:0] $end
$var reg 1 F r_TX_Done $end
$upscope $end
$scope module fifo_memory_instance $end
$var wire 1 # i_Clock $end
$var wire 8 G i_Data_In [7:0] $end
$var wire 1 , i_Read_En $end
$var wire 1 % i_Reset $end
$var wire 1 5 i_Write_En $end
$var wire 8 H o_Data_Out [7:0] $end
$var wire 8 I nxtread [7:0] $end
$var wire 8 J dblnext [7:0] $end
$var reg 1 4 fifo_empty $end
$var reg 1 3 fifo_full $end
$var reg 1 2 fifo_overflow $end
$var reg 1 1 fifo_underflow $end
$var reg 8 K r_Data_Out [7:0] $end
$var reg 8 L rdaddr [7:0] $end
$var reg 8 M wraddr [7:0] $end
$upscope $end
$scope module lower_to_upper_instance $end
$var wire 1 # i_Clock $end
$var wire 1 4 i_Data_Empty $end
$var wire 1 % i_Reset $end
$var wire 8 N i_data [7:0] $end
$var wire 1 . o_write_enable $end
$var wire 1 / o_read_enable $end
$var wire 8 O o_data [7:0] $end
$var reg 1 P r_read_en_delay $end
$var reg 1 / r_read_enable $end
$upscope $end
$upscope $end
$scope task UART_READ_BYTE $end
$var integer 32 Q iii [31:0] $end
$upscope $end
$scope task UART_WRITE_BYTE $end
$var reg 8 R i_Data [7:0] $end
$var integer 32 S ii [31:0] $end
$upscope $end
$upscope $end
$enddefinitions $end
#0
$dumpvars
bx S
bx R
bx Q
xP
b11100000 O
b0 N
b0 M
b0 L
b0 K
b10 J
b1 I
b0 H
b0 G
0F
b0 E
0D
b0 C
b0 B
b0 A
b11100000 @
b0 ?
b0 >
b0 =
b0 <
b0 ;
0:
b0 9
08
07
b0 6
05
14
03
x2
x1
b11100000 0
x/
0.
b0 -
0,
b0 +
x*
b11100000 )
0(
0'
b0 &
0%
1$
0#
0"
1!
$end
#20
0P
1%
1#
#40
0#
#60
0*
0/
1#
#80
0#
#100
0$
b1100001 R
1#
#120
0#
#140
b1 ?
1#
#160
0#
#180
b1 =
1#
#200
0#
#220
b10 =
1#
#240
0#
#260
b11 =
1#
#280
0#
#300
b100 =
1#
#320
0#
#340
b101 =
1#
#360
0#
#380
b110 =
1#
#400
0#
#420
b111 =
1#
#440
0#
#460
b1000 =
1#
#480
0#
#500
b1001 =
1#
#520
0#
#540
b1010 =
1#
#560
0#
#580
b1011 =
1#
#600
0#
#620
b1100 =
1#
#640
0#
#660
b1101 =
1#
#680
0#
#700
b1110 =
1#
#720
0#
#740
b1111 =
1#
#760
0#
#780
b10000 =
1#
#800
0#
#820
b10001 =
1#
#840
0#
#860
b10010 =
1#
#880
0#
#900
b10011 =
1#
#920
0#
#940
b10100 =
1#
#960
0#
#980
b10101 =
1#
#1000
0#
#1020
b10110 =
1#
#1040
0#
#1060
b10111 =
1#
#1080
0#
#1100
b11000 =
1#
#1120
0#
#1140
b11001 =
1#
#1160
0#
#1180
b11010 =
1#
#1200
0#
#1220
b11011 =
1#
#1240
0#
#1260
b11100 =
1#
#1280
0#
#1300
b11101 =
1#
#1320
0#
#1340
b11110 =
1#
#1360
0#
#1380
b11111 =
1#
#1400
0#
#1420
b100000 =
1#
#1440
0#
#1460
b100001 =
1#
#1480
0#
#1500
b100010 =
1#
#1520
0#
#1540
b100011 =
1#
#1560
0#
#1580
b100100 =
1#
#1600
0#
#1620
b100101 =
1#
#1640
0#
#1660
b100110 =
1#
#1680
0#
#1700
b100111 =
1#
#1720
0#
#1740
b101000 =
1#
#1760
0#
#1780
b101001 =
1#
#1800
0#
#1820
b101010 =
1#
#1840
0#
#1860
b101011 =
1#
#1880
0#
#1900
b101100 =
1#
#1920
0#
#1940
b101101 =
1#
#1960
0#
#1980
b101110 =
1#
#2000
0#
#2020
b101111 =
1#
#2040
0#
#2060
b110000 =
1#
#2080
0#
#2100
b110001 =
1#
#2120
0#
#2140
b110010 =
1#
#2160
0#
#2180
b110011 =
1#
#2200
0#
#2220
b110100 =
1#
#2240
0#
#2260
b110101 =
1#
#2280
0#
#2300
b110110 =
1#
#2320
0#
#2340
b110111 =
1#
#2360
0#
#2380
b111000 =
1#
#2400
0#
#2420
b111001 =
1#
#2440
0#
#2460
b111010 =
1#
#2480
0#
#2500
b111011 =
1#
#2520
0#
#2540
b111100 =
1#
#2560
0#
#2580
b111101 =
1#
#2600
0#
#2620
b111110 =
1#
#2640
0#
#2660
b111111 =
1#
#2680
0#
#2700
b1000000 =
1#
#2720
0#
#2740
b1000001 =
1#
#2760
0#
#2780
b1000010 =
1#
#2800
0#
#2820
b1000011 =
1#
#2840
0#
#2860
b1000100 =
1#
#2880
0#
#2900
b1000101 =
1#
#2920
0#
#2940
b1000110 =
1#
#2960
0#
#2980
b1000111 =
1#
#3000
0#
#3020
b1001000 =
1#
#3040
0#
#3060
b1001001 =
1#
#3080
0#
#3100
b1001010 =
1#
#3120
0#
#3140
b1001011 =
1#
#3160
0#
#3180
b1001100 =
1#
#3200
0#
#3220
b1001101 =
1#
#3240
0#
#3260
b1001110 =
1#
#3280
0#
#3300
b1001111 =
1#
#3320
0#
#3340
b1010000 =
1#
#3360
0#
#3380
b1010001 =
1#
#3400
0#
#3420
b1010010 =
1#
#3440
0#
#3460
b1010011 =
1#
#3480
0#
#3500
b1010100 =
1#
#3520
0#
#3540
b1010101 =
1#
#3560
0#
#3580
b1010110 =
1#
#3600
0#
#3620
b1010111 =
1#
#3640
0#
#3660
b1011000 =
1#
#3680
0#
#3700
b1011001 =
1#
#3720
0#
#3740
b1011010 =
1#
#3760
0#
#3780
b1011011 =
1#
#3800
0#
#3820
b1011100 =
1#
#3840
0#
#3860
b1011101 =
1#
#3880
0#
#3900
b1011110 =
1#
#3920
0#
#3940
b1011111 =
1#
#3960
0#
#3980
b1100000 =
1#
#4000
0#
#4020
b1100001 =
1#
#4040
0#
#4060
b1100010 =
1#
#4080
0#
#4100
b1100011 =
1#
#4120
0#
#4140
b1100100 =
1#
#4160
0#
#4180
b1100101 =
1#
#4200
0#
#4220
b1100110 =
1#
#4240
0#
#4260
b1100111 =
1#
#4280
0#
#4300
b10 ?
b0 =
1#
#4320
0#
#4340
b1 =
1#
#4360
0#
#4380
b10 =
1#
#4400
0#
#4420
b11 =
1#
#4440
0#
#4460
b100 =
1#
#4480
0#
#4500
b101 =
1#
#4520
0#
#4540
b110 =
1#
#4560
0#
#4580
b111 =
1#
#4600
0#
#4620
b1000 =
1#
#4640
0#
#4660
b1001 =
1#
#4680
0#
#4700
b1010 =
1#
#4720
0#
#4740
b1011 =
1#
#4760
0#
#4780
b1100 =
1#
#4800
0#
#4820
b1101 =
1#
#4840
0#
#4860
b1110 =
1#
#4880
0#
#4900
b1111 =
1#
#4920
0#
#4940
b10000 =
1#
#4960
0#
#4980
b10001 =
1#
#5000
0#
#5020
b10010 =
1#
#5040
0#
#5060
b10011 =
1#
#5080
0#
#5100
b10100 =
1#
#5120
0#
#5140
b10101 =
1#
#5160
0#
#5180
b10110 =
1#
#5200
0#
#5220
b10111 =
1#
#5240
0#
#5260
b11000 =
1#
#5280
0#
#5300
b11001 =
1#
#5320
0#
#5340
b11010 =
1#
#5360
0#
#5380
b11011 =
1#
#5400
0#
#5420
b11100 =
1#
#5440
0#
#5460
b11101 =
1#
#5480
0#
#5500
b11110 =
1#
#5520
0#
#5540
b11111 =
1#
#5560
0#
#5580
b100000 =
1#
#5600
0#
#5620
b100001 =
1#
#5640
0#
#5660
b100010 =
1#
#5680
0#
#5700
b100011 =
1#
#5720
0#
#5740
b100100 =
1#
#5760
0#
#5780
b100101 =
1#
#5800
0#
#5820
b100110 =
1#
#5840
0#
#5860
b100111 =
1#
#5880
0#
#5900
b101000 =
1#
#5920
0#
#5940
b101001 =
1#
#5960
0#
#5980
b101010 =
1#
#6000
0#
#6020
b101011 =
1#
#6040
0#
#6060
b101100 =
1#
#6080
0#
#6100
b101101 =
1#
#6120
0#
#6140
b101110 =
1#
#6160
0#
#6180
b101111 =
1#
#6200
0#
#6220
b110000 =
1#
#6240
0#
#6260
b110001 =
1#
#6280
0#
#6300
b110010 =
1#
#6320
0#
#6340
b110011 =
1#
#6360
0#
#6380
b110100 =
1#
#6400
0#
#6420
b110101 =
1#
#6440
0#
#6460
b110110 =
1#
#6480
0#
#6500
b110111 =
1#
#6520
0#
#6540
b111000 =
1#
#6560
0#
#6580
b111001 =
1#
#6600
0#
#6620
b111010 =
1#
#6640
0#
#6660
b111011 =
1#
#6680
0#
#6700
b111100 =
1#
#6720
0#
#6740
b111101 =
1#
#6760
0#
#6780
b111110 =
1#
#6800
0#
#6820
b111111 =
1#
#6840
0#
#6860
b1000000 =
1#
#6880
0#
#6900
b1000001 =
1#
#6920
0#
#6940
b1000010 =
1#
#6960
0#
#6980
b1000011 =
1#
#7000
0#
#7020
b1000100 =
1#
#7040
0#
#7060
b1000101 =
1#
#7080
0#
#7100
b1000110 =
1#
#7120
0#
#7140
b1000111 =
1#
#7160
0#
#7180
b1001000 =
1#
#7200
0#
#7220
b1001001 =
1#
#7240
0#
#7260
b1001010 =
1#
#7280
0#
#7300
b1001011 =
1#
#7320
0#
#7340
b1001100 =
1#
#7360
0#
#7380
b1001101 =
1#
#7400
0#
#7420
b1001110 =
1#
#7440
0#
#7460
b1001111 =
1#
#7480
0#
#7500
b1010000 =
1#
#7520
0#
#7540
b1010001 =
1#
#7560
0#
#7580
b1010010 =
1#
#7600
0#
#7620
b1010011 =
1#
#7640
0#
#7660
b1010100 =
1#
#7680
0#
#7700
b1010101 =
1#
#7720
0#
#7740
b1010110 =
1#
#7760
0#
#7780
b1010111 =
1#
#7800
0#
#7820
b1011000 =
1#
#7840
0#
#7860
b1011001 =
1#
#7880
0#
#7900
b1011010 =
1#
#7920
0#
#7940
b1011011 =
1#
#7960
0#
#7980
b1011100 =
1#
#8000
0#
#8020
b1011101 =
1#
#8040
0#
#8060
b1011110 =
1#
#8080
0#
#8100
b1011111 =
1#
#8120
0#
#8140
b1100000 =
1#
#8160
0#
#8180
b1100001 =
1#
#8200
0#
#8220
b1100010 =
1#
#8240
0#
#8260
b1100011 =
1#
#8280
0#
#8300
b1100100 =
1#
#8320
0#
#8340
b1100101 =
1#
#8360
0#
#8380
b1100110 =
1#
#8400
0#
#8420
b1100111 =
1#
#8440
0#
#8460
b1101000 =
1#
#8480
0#
#8500
b1101001 =
1#
#8520
0#
#8540
b1101010 =
1#
#8560
0#
#8580
b1101011 =
1#
#8600
0#
#8620
b1101100 =
1#
#8640
0#
#8660
b1101101 =
1#
#8680
0#
#8700
b1101110 =
1#
#8720
0#
#8740
b1101111 =
1#
#8760
0#
#8780
b1110000 =
1#
#8800
0#
#8820
b1110001 =
1#
#8840
0#
#8860
b1110010 =
1#
#8880
0#
#8900
b1110011 =
1#
#8920
0#
#8940
b1110100 =
1#
#8960
0#
#8980
b1110101 =
1#
#9000
0#
#9020
b1110110 =
1#
#9040
0#
#9060
b1110111 =
1#
#9080
0#
#9100
b1111000 =
1#
#9120
0#
#9140
b1111001 =
1#
#9160
0#
#9180
b1111010 =
1#
#9200
0#
#9220
b1111011 =
1#
#9240
0#
#9260
b1111100 =
1#
#9280
0#
#9300
b1111101 =
1#
